src/main.py
agentfx-0.0.1.dist-info/METADATA
agentfx-0.0.1.dist-info/WHEEL
agentfx-0.0.1.dist-info/RECORD
